MANIFEST.in
README.md
setup.cfg
setup.py
cabot_check_prometheus/__init__.py
cabot_check_prometheus/models.py
cabot_check_prometheus/urls.py
cabot_check_prometheus/views.py
cabot_check_prometheus.egg-info/PKG-INFO
cabot_check_prometheus.egg-info/SOURCES.txt
cabot_check_prometheus.egg-info/dependency_links.txt
cabot_check_prometheus.egg-info/top_level.txt
cabot_check_prometheus/migrations/0001_initial.py
cabot_check_prometheus/migrations/__init__.py