Metadata-Version: 1.0
Name: cabot-check-prometheus
Version: 1.0.1
Summary: A Prometheus plugin for Cabot
Home-page: https://github.com/widen/cabot-check-prometheus
Author: Widen Enterprises
Author-email: pgarland@widen.com
License: UNKNOWN
Platform: UNKNOWN
